golem_kernel/__init__.py
golem_kernel/__main__.py
golem_kernel/golem.py
golem_kernel/golem_kernel.py
golem_kernel/remote_python.py
golem_kernel-0.1.0.dist-info/METADATA
golem_kernel-0.1.0.dist-info/WHEEL
golem_kernel-0.1.0.dist-info/RECORD
